{"data":[{"default_state":false,"distance":2,"door_data":[{"door_coords":{"y":6462.0126953125,"x":-110.64230346679688,"z":31.79333686828613},"model_hash":2063730765,"unique_id":"jLHu9aevb7RYl_NmxCGOw","text_dimensions":1.31868304149247}],"location_group":"Paleto Bank","perms":{"identifier":[],"items":[],"discord":[],"job":[{"name":"police","grade":0}],"ace":[]},"id":50,"door_name":"Entrance","secret":false,"state":false,"door_type":"single","door_sound":"door_regular.ogg","lockpickable":false,"camera":true},{"default_state":false,"distance":2,"door_data":[{"door_coords":{"y":6463.77392578125,"x":-104.83712768554688,"z":31.79334640502929},"model_hash":2110946875,"unique_id":"8-iprbPT34OZfgRyeJ_p4","text_dimensions":1.31868304149247}],"location_group":"Paleto Bank","perms":{"identifier":[],"items":[],"discord":[],"job":[{"name":"police","grade":0}],"ace":[]},"id":51,"door_name":"Loans 1","secret":false,"state":false,"door_type":"single","door_sound":"door_regular.ogg","lockpickable":false,"camera":false},{"default_state":false,"distance":2,"door_data":[{"door_coords":{"y":6467.9892578125,"x":-100.62174224853516,"z":31.79334640502929},"model_hash":1754616769,"unique_id":"j088lUsWcYYhJVp22bXEc","text_dimensions":1.31868304149247}],"location_group":"Paleto Bank","perms":{"identifier":[],"items":[],"discord":[],"job":[{"name":"police","grade":0}],"ace":[]},"id":52,"door_name":"Loans 2","secret":false,"state":false,"door_type":"single","door_sound":"door_regular.ogg","lockpickable":false,"camera":true},{"default_state":false,"distance":2,"door_data":[{"door_coords":{"y":6473.91796875,"x":-104.70573425292968,"z":31.78798294067382},"model_hash":-368548260,"unique_id":"Gfndx0nW8QgkUBKuGDd6U","text_dimensions":1.31868304149247}],"location_group":"Paleto Bank","perms":{"identifier":[],"items":[],"discord":[],"job":[{"name":"police","grade":0}],"ace":[]},"id":53,"door_name":"Administration","secret":false,"state":false,"door_type":"single","door_sound":"door_regular.ogg","lockpickable":false,"camera":true},{"default_state":true,"distance":2,"door_data":[{"door_coords":{"y":6478.9599609375,"x":-116.51268768310549,"z":31.78797912597656},"model_hash":1248599813,"unique_id":"1C1Wzsg7blXw2rL1bleSh","text_dimensions":-1.30158996913814}],"location_group":"Paleto Bank","perms":{"identifier":[],"items":[],"discord":[],"job":[{"name":"police","grade":0}],"ace":[]},"id":54,"door_name":"Side Exit 1","secret":false,"state":false,"door_type":"single","door_sound":"door_metal.ogg","lockpickable":false,"camera":true},{"default_state":false,"distance":2,"door_data":[{"door_coords":{"y":6475.328125,"x":-111.04269409179688,"z":31.78797912597656},"model_hash":-56652918,"unique_id":"Gikw4y6imHLK_nfyySOyN","text_dimensions":1.31868304149247}],"location_group":"Paleto Bank","perms":{"identifier":[],"items":[],"discord":[],"job":[{"name":"police","grade":0}],"ace":[]},"id":55,"door_name":"Back Rooms 1","secret":false,"state":false,"door_type":"single","door_sound":"door_regular.ogg","lockpickable":false,"camera":true},{"default_state":false,"distance":2,"door_data":[{"door_coords":{"y":6468.0078125,"x":-112.57083129882813,"z":31.21414375305175},"model_hash":1784650867,"unique_id":"zhuiD6XZVo0QipRaw9h5I","text_dimensions":1.44222111906856}],"location_group":"Paleto Bank","perms":{"identifier":[],"items":[],"discord":[],"job":[{"name":"police","grade":0}],"ace":[]},"id":56,"door_name":"Reception","secret":true,"state":false,"door_type":"single","door_sound":"door_regular.ogg","lockpickable":false,"camera":false},{"default_state":true,"distance":2,"door_data":[{"door_coords":{"y":6468.96044921875,"x":-92.23223114013672,"z":31.78797912597656},"model_hash":-147325430,"unique_id":"QOYQustiVHEI4oMdVURjp","text_dimensions":1.29998779296875}],"location_group":"Paleto Bank","perms":{"identifier":[],"items":[],"discord":[],"job":[{"name":"police","grade":0}],"ace":[]},"id":57,"door_name":"CCTV","secret":false,"state":false,"door_type":"single","door_sound":"door_metal.ogg","lockpickable":false,"camera":true},{"default_state":true,"distance":2,"door_data":[{"door_coords":{"y":6474.056640625,"x":-96.70865631103516,"z":31.78797912597656},"model_hash":1248599813,"unique_id":"H5xjprPhDo3w9m_HmaXnL","text_dimensions":-1.30158996913814}],"location_group":"Paleto Bank","perms":{"identifier":[],"items":[],"discord":[],"job":[{"name":"police","grade":0}],"ace":[]},"id":58,"door_name":"Side Exit 2","secret":false,"state":true,"door_type":"single","door_sound":"door_metal.ogg","lockpickable":false,"camera":true},{"default_state":true,"distance":2,"door_data":[{"door_coords":{"y":6474.39208984375,"x":-100.11229705810549,"z":31.78797912597656},"model_hash":-147325430,"unique_id":"fN4R0S7Z4DHdlX0gomOi-","text_dimensions":1.29998779296875}],"location_group":"Paleto Bank","perms":{"identifier":[],"items":[],"discord":[],"job":[{"name":"police","grade":0}],"ace":[]},"id":59,"door_name":"Back Rooms 2","secret":false,"state":true,"door_type":"single","door_sound":"door_regular.ogg","lockpickable":false,"camera":true},{"default_state":true,"distance":2,"door_data":[{"door_coords":{"y":6464.54931640625,"x":-100.24186706542968,"z":31.88460350036621},"model_hash":-2050208642,"unique_id":"FJsp7GipHJ0-drcU4Qz5P","text_dimensions":1.63406101614236}],"location_group":"Paleto Bank","perms":{"identifier":[],"items":[],"discord":[],"job":[{"name":"police","grade":0}],"ace":[]},"id":60,"door_name":"Safe","secret":false,"state":true,"door_type":"single","door_sound":"door_regular.ogg","lockpickable":false,"camera":true}],"name":"paleto_bank.json","imported":false}